examples/arweave_upload.py
examples/balance_example.py
examples/ethereum_upload.py
examples/test_wallet_integration.py
tests/__init__.py
tests/test_arweave_signer.py
tests/test_constants.py
tests/test_dataitem.py
tests/test_ethereum_signer.py
tests/test_stream_signing.py
tests/test_tags.py
tests/test_turbo.py
tests/test_utils.py
turbo_sdk/__init__.py
turbo_sdk/client.py
turbo_sdk/py.typed
turbo_sdk/types.py
turbo_sdk/bundle/__init__.py
turbo_sdk/bundle/constants.py
turbo_sdk/bundle/create.py
turbo_sdk/bundle/dataitem.py
turbo_sdk/bundle/sign.py
turbo_sdk/bundle/tags.py
turbo_sdk/bundle/utils.py
turbo_sdk/signers/__init__.py
turbo_sdk/signers/arweave.py
turbo_sdk/signers/ethereum.py
turbo_sdk/signers/signer.py
turbo_sdk-0.0.4.dist-info/licenses/LICENSE
turbo_sdk-0.0.4.dist-info/METADATA
turbo_sdk-0.0.4.dist-info/WHEEL
turbo_sdk-0.0.4.dist-info/top_level.txt
turbo_sdk-0.0.4.dist-info/RECORD
