Metadata-Version: 2.4
Name: turbo-sdk
Version: 0.0.4
Summary: Python SDK for interacting with the Ardrive Turbo Upload and Payment Service
Author-email: ArDrive <info@ardrive.io>
License: MIT
Project-URL: Homepage, https://github.com/ardriveapp/turbo-python-sdk
Project-URL: Repository, https://github.com/ardriveapp/turbo-python-sdk
Project-URL: Documentation, https://github.com/ardriveapp/turbo-python-sdk#readme
Classifier: Development Status :: 3 - Alpha
Classifier: Intended Audience :: Developers
Classifier: Programming Language :: Python :: 3
Classifier: Programming Language :: Python :: 3.8
Classifier: Programming Language :: Python :: 3.9
Classifier: Programming Language :: Python :: 3.10
Classifier: Programming Language :: Python :: 3.11
Classifier: Programming Language :: Python :: 3.12
Requires-Python: >=3.8
License-File: LICENSE
Requires-Dist: requests>=2.28.0
Requires-Dist: base58>=2.1.1
Requires-Dist: eth-account>=0.8.0
Requires-Dist: web3>=6.5.0
Requires-Dist: eth-keys>=0.4.0
Requires-Dist: eth-hash
Requires-Dist: cryptography>=41.0.0
Provides-Extra: dev
Requires-Dist: pytest>=7.4.0; extra == "dev"
Requires-Dist: pytest-cov>=4.1.0; extra == "dev"
Requires-Dist: black>=23.7.0; extra == "dev"
Requires-Dist: flake8>=6.1.0; extra == "dev"
Requires-Dist: mypy>=1.5.0; extra == "dev"
Requires-Dist: build>=0.10.0; extra == "dev"
Requires-Dist: twine>=4.0.0; extra == "dev"
Requires-Dist: safety>=2.3.0; extra == "dev"
Requires-Dist: bandit>=1.7.0; extra == "dev"
Dynamic: license-file
